pycons3rt/VERSION.txt
pycons3rt/__init__.py
pycons3rt/aliasip.py
pycons3rt/asset.py
pycons3rt/assetmailer.py
pycons3rt/bash.py
pycons3rt/cons3rtutil.py
pycons3rt/deployment.py
pycons3rt/dyndict.py
pycons3rt/logify.py
pycons3rt/nexus.py
pycons3rt/osutil.py
pycons3rt/pycons3rt-logging.conf
pycons3rt/pygit.py
pycons3rt/pyjavakeys.py
pycons3rt/slack.py
pycons3rt/windows.py
pycons3rt/awsapi/__init__.py
pycons3rt/awsapi/awslibs.py
pycons3rt/awsapi/ec2util.py
pycons3rt/awsapi/images.py
pycons3rt/awsapi/metadata.py
pycons3rt/awsapi/s3util.py
tests/__init__.py
tests/deployment.py
pycons3rt-0.0.13.dist-info/AUTHORS.txt
pycons3rt-0.0.13.dist-info/LICENSE
pycons3rt-0.0.13.dist-info/METADATA
pycons3rt-0.0.13.dist-info/WHEEL
pycons3rt-0.0.13.dist-info/entry_points.txt
pycons3rt-0.0.13.dist-info/top_level.txt
pycons3rt-0.0.13.dist-info/zip-safe
pycons3rt-0.0.13.dist-info/RECORD
