Metadata-Version: 2.1
Name: pycons3rt
Version: 0.0.13
Summary: A python library for CONS3RT assets
Home-page: https://github.com/cons3rt/pycons3rt
Author: Joe Yennaco
Author-email: joe.yennaco@jackpinetech.com
License: GNU GPL v3
Platform: UNKNOWN
Classifier: Programming Language :: Python :: 2.7
Classifier: Operating System :: OS Independent
Requires-Dist: awscli
Requires-Dist: boto3
Requires-Dist: botocore
Requires-Dist: netifaces
Requires-Dist: jinja2
Requires-Dist: requests
Requires-Dist: requests[security]
